morphometrics_engine/__init__.py
morphometrics_engine/_version.py
morphometrics_engine/_widget.py
morphometrics_engine/measure.py
morphometrics_engine/napari.yaml
morphometrics_engine/types.py
morphometrics_engine/_tests/__init__.py
morphometrics_engine/_tests/test_register.py
morphometrics_engine/_tests/test_types.py
morphometrics_engine/_tests/test_widget.py
morphometrics_engine-0.0.1.dist-info/LICENSE
morphometrics_engine-0.0.1.dist-info/METADATA
morphometrics_engine-0.0.1.dist-info/WHEEL
morphometrics_engine-0.0.1.dist-info/entry_points.txt
morphometrics_engine-0.0.1.dist-info/top_level.txt
morphometrics_engine-0.0.1.dist-info/RECORD
